cyjax_misp/__init__.py
cyjax_misp/cli.py
cyjax_misp/configuration.py
cyjax_misp/misp.py
cyjax_misp_input_module-1.2.0.data/scripts/cyjax-misp-input-module
tests/__init__.py
tests/configuration_test.py
tests/misp_test.py
tests/run_test.py
cyjax_misp_input_module-1.2.0.dist-info/METADATA
cyjax_misp_input_module-1.2.0.dist-info/WHEEL
cyjax_misp_input_module-1.2.0.dist-info/top_level.txt
cyjax_misp_input_module-1.2.0.dist-info/RECORD
