Metadata-Version: 2.1
Name: cyjax-misp-input-module
Version: 1.2.0
Summary: cyjax-misp-input-module provides an input module for MISP for incident reports and indicators of compromise.
Home-page: https://www.cyjax.com
Author: Cyjax Ltd.
Author-email: github@cyjax.com
License: MIT
Classifier: Development Status :: 5 - Production/Stable
Classifier: Environment :: Web Environment
Classifier: Intended Audience :: System Administrators
Classifier: License :: OSI Approved :: MIT License
Classifier: Operating System :: OS Independent
Classifier: Programming Language :: Python
Classifier: Programming Language :: Python :: 3
Classifier: Programming Language :: Python :: 3.6
Classifier: Programming Language :: Python :: 3.7
Classifier: Programming Language :: Python :: 3.8
Classifier: Programming Language :: Python :: 3.9
Classifier: Topic :: Utilities
Requires-Python: >=3.6
Requires-Dist: pymisp==2.4.*
Requires-Dist: cyjax-cti==2.1.*
Provides-Extra: test
Requires-Dist: pytest; extra == "test"
Requires-Dist: pylint==3.0.*; extra == "test"
Requires-Dist: flake8; extra == "test"
Requires-Dist: twine; extra == "test"
